procconveyor/__init__.py
procconveyor/procconveyor.py
procconveyor/test.py
procconveyor-0.0.3.dist-info/METADATA
procconveyor-0.0.3.dist-info/WHEEL
procconveyor-0.0.3.dist-info/top_level.txt
procconveyor-0.0.3.dist-info/RECORD
