Metadata-Version: 2.1
Name: procconveyor
Version: 0.0.3
Summary: A package to make conveyor of parallel data processing
Home-page: https://github.com/aver007/proc-conveyor/
Author: aver
Author-email: a.v.e.r@mail.ru
License: UNKNOWN
Platform: UNKNOWN
Classifier: Programming Language :: Python :: 3.8
